pyprinttree/__init__.py
pyprinttree/constants.py
pyprinttree/exceptions.py
pyprinttree/loaders.py
pyprinttree/renderer.py
pyprinttree/structures.py
pyprinttree/tests/__init__.py
pyprinttree/tests/__main__.py
pyprinttree/tests/test_loaders.py
pyprinttree/tests/test_renderer.py
pyprinttree/tests/test_structures.py
pyprinttree-0.0.1.dist-info/LICENSE
pyprinttree-0.0.1.dist-info/METADATA
pyprinttree-0.0.1.dist-info/WHEEL
pyprinttree-0.0.1.dist-info/top_level.txt
pyprinttree-0.0.1.dist-info/RECORD
