Metadata-Version: 2.1
Name: pyprinttree
Version: 0.0.1
Summary: A tool for printing tree structures to a console in a meaningful way.
Home-page: UNKNOWN
Author: Tanner Netterville
Author-email: tannern@gmail.com
License: UNKNOWN
Platform: UNKNOWN
Classifier: Programming Language :: Python :: 3
Classifier: Programming Language :: Python :: 2
Classifier: License :: OSI Approved :: MIT License
Classifier: Operating System :: OS Independent
